{
  "ElectionName": "2017 November General",
  "ElectionDate": "2017-11-07T00:00:00",
  "CreateDate": "2017-11-13T19:06:11.9506926-05:00",
  "Locality": {
    "LocalityName": "AMELIA COUNTY",
    "LocalityCode": "007"
  },
  "Races": [
    {
      "RaceName": "Governor",
      "PrecinctsReporting": 6,
      "PrecinctsParticipating": 6,
      "NumberOfSeats": 1,
      "Candidates": [
        {
          "BallotName": "Ralph S. Northam",
          "BallotOrder": 1,
          "Votes": 1403,
          "Percentage": "30.41%",
          "PoliticalParty": "Democratic"
        },
        {
          "BallotName": "Edward W. \"Ed\" Gillespie",
          "BallotOrder": 2,
          "Votes": 3170,
          "Percentage": "68.70%",
          "PoliticalParty": "Republican"
        },
        {
          "BallotName": "Clifford D. Hyra",
          "BallotOrder": 3,
          "Votes": 40,
          "Percentage": "0.87%",
          "PoliticalParty": "Libertarian"
        },
        {
          "BallotName": "Write In",
          "BallotOrder": 2147483647,
          "Votes": 1,
          "Percentage": "0.02%",
          "PoliticalParty": "Write-In"
        }
      ]
    },
    {
      "RaceName": "Lieutenant Governor",
      "PrecinctsReporting": 6,
      "PrecinctsParticipating": 6,
      "NumberOfSeats": 1,
      "Candidates": [
        {
          "BallotName": "Justin E. Fairfax",
          "BallotOrder": 1,
          "Votes": 1351,
          "Percentage": "29.41%",
          "PoliticalParty": "Democratic"
        },
        {
          "BallotName": "Jill H. Vogel",
          "BallotOrder": 2,
          "Votes": 3241,
          "Percentage": "70.55%",
          "PoliticalParty": "Republican"
        },
        {
          "BallotName": "Write In",
          "BallotOrder": 2147483647,
          "Votes": 2,
          "Percentage": "0.04%",
          "PoliticalParty": "Write-In"
        }
      ]
    },
    {
      "RaceName": "Attorney General",
      "PrecinctsReporting": 6,
      "PrecinctsParticipating": 6,
      "NumberOfSeats": 1,
      "Candidates": [
        {
          "BallotName": "Mark R. Herring",
          "BallotOrder": 1,
          "Votes": 1391,
          "Percentage": "30.34%",
          "PoliticalParty": "Democratic"
        },
        {
          "BallotName": "John D. Adams",
          "BallotOrder": 2,
          "Votes": 3190,
          "Percentage": "69.59%",
          "PoliticalParty": "Republican"
        },
        {
          "BallotName": "Write In",
          "BallotOrder": 2147483647,
          "Votes": 3,
          "Percentage": "0.07%",
          "PoliticalParty": "Write-In"
        }
      ]
    },
    {
      "RaceName": "Member House of Delegates (061)",
      "PrecinctsReporting": 6,
      "PrecinctsParticipating": 6,
      "NumberOfSeats": 1,
      "Candidates": [
        {
          "BallotName": "Thomas C. Wright, Jr.",
          "BallotOrder": 1,
          "Votes": 3827,
          "Percentage": "96.94%",
          "PoliticalParty": "Republican"
        },
        {
          "BallotName": "Write In",
          "BallotOrder": 2147483647,
          "Votes": 121,
          "Percentage": "3.06%",
          "PoliticalParty": "Write-In"
        }
      ]
    },
    {
      "RaceName": "Member Board of Supervisors (DISTRICT 2)",
      "PrecinctsReporting": 2,
      "PrecinctsParticipating": 2,
      "NumberOfSeats": 1,
      "Candidates": [
        {
          "BallotName": "Roger A. Scott",
          "BallotOrder": 1,
          "Votes": 757,
          "Percentage": "98.31%",
          "PoliticalParty": ""
        },
        {
          "BallotName": "Write In",
          "BallotOrder": 2147483647,
          "Votes": 13,
          "Percentage": "1.69%",
          "PoliticalParty": ""
        }
      ]
    },
    {
      "RaceName": "Member Board of Supervisors (DISTRICT 5)",
      "PrecinctsReporting": 2,
      "PrecinctsParticipating": 2,
      "NumberOfSeats": 1,
      "Candidates": [
        {
          "BallotName": "Franklin D. Harris",
          "BallotOrder": 1,
          "Votes": 852,
          "Percentage": "97.37%",
          "PoliticalParty": ""
        },
        {
          "BallotName": "Write In",
          "BallotOrder": 2147483647,
          "Votes": 23,
          "Percentage": "2.63%",
          "PoliticalParty": ""
        }
      ]
    },
    {
      "RaceName": "Member School Board (DISTRICT 2)",
      "PrecinctsReporting": 2,
      "PrecinctsParticipating": 2,
      "NumberOfSeats": 1,
      "Candidates": [
        {
          "BallotName": "Glen B. Wilkerson",
          "BallotOrder": 1,
          "Votes": 848,
          "Percentage": "98.95%",
          "PoliticalParty": ""
        },
        {
          "BallotName": "Write In",
          "BallotOrder": 2147483647,
          "Votes": 9,
          "Percentage": "1.05%",
          "PoliticalParty": ""
        }
      ]
    },
    {
      "RaceName": "Member School Board (DISTRICT 4)",
      "PrecinctsReporting": 2,
      "PrecinctsParticipating": 2,
      "NumberOfSeats": 1,
      "Candidates": [
        {
          "BallotName": "Bonnie W. Vega",
          "BallotOrder": 1,
          "Votes": 725,
          "Percentage": "95.90%",
          "PoliticalParty": ""
        },
        {
          "BallotName": "Write In",
          "BallotOrder": 2147483647,
          "Votes": 31,
          "Percentage": "4.10%",
          "PoliticalParty": ""
        }
      ]
    },
    {
      "RaceName": "Member School Board (DISTRICT 5)",
      "PrecinctsReporting": 2,
      "PrecinctsParticipating": 2,
      "NumberOfSeats": 1,
      "Candidates": [
        {
          "BallotName": "James L. \"Jim\" Ferrara",
          "BallotOrder": 1,
          "Votes": 813,
          "Percentage": "97.72%",
          "PoliticalParty": ""
        },
        {
          "BallotName": "Write In",
          "BallotOrder": 2147483647,
          "Votes": 19,
          "Percentage": "2.28%",
          "PoliticalParty": ""
        }
      ]
    },
    {
      "RaceName": "Meals Tax (AMELIA COUNTY)",
      "PrecinctsReporting": 6,
      "PrecinctsParticipating": 6,
      "NumberOfSeats": 1,
      "Candidates": [
        {
          "BallotName": "Yes",
          "BallotOrder": 1,
          "Votes": 1678,
          "Percentage": "37.90%",
          "PoliticalParty": null
        },
        {
          "BallotName": "No",
          "BallotOrder": 2,
          "Votes": 2749,
          "Percentage": "62.10%",
          "PoliticalParty": null
        }
      ]
    }
  ]
}
