{"ElectionName":"2017 November General","ElectionDate":"2017-11-07T00:00:00","CreateDate":"2017-11-13T19:07:22.7354225-05:00","Locality":{"LocalityName":"KING WILLIAM COUNTY","LocalityCode":"101"},"District":null,"RaceName":"Governor","NumberOfSeats":1,"Precincts":[{"PrecinctName":"# AB - Central Absentee Precinct (01)","Candidates":[{"BallotName":"Ralph S. Northam","BallotOrder":1,"Votes":76,"Percentage":"35.85%","PoliticalParty":"Democratic"},{"BallotName":"Edward W. \"Ed\" Gillespie","BallotOrder":2,"Votes":133,"Percentage":"62.74%","PoliticalParty":"Republican"},{"BallotName":"Clifford D. Hyra","BallotOrder":3,"Votes":3,"Percentage":"1.42%","PoliticalParty":"Libertarian"},{"BallotName":"Write In","BallotOrder":2147483647,"Votes":0,"Percentage":"0.00%","PoliticalParty":"Write-In"}]},{"PrecinctName":"## Provisional (01)","Candidates":[{"BallotName":"Ralph S. Northam","BallotOrder":1,"Votes":3,"Percentage":"33.33%","PoliticalParty":"Democratic"},{"BallotName":"Edward W. \"Ed\" Gillespie","BallotOrder":2,"Votes":5,"Percentage":"55.56%","PoliticalParty":"Republican"},{"BallotName":"Clifford D. Hyra","BallotOrder":3,"Votes":1,"Percentage":"11.11%","PoliticalParty":"Libertarian"},{"BallotName":"Write In","BallotOrder":2147483647,"Votes":0,"Percentage":"0.00%","PoliticalParty":"Write-In"}]},{"PrecinctName":"101 - WEST POINT (01)","Candidates":[{"BallotName":"Ralph S. Northam","BallotOrder":1,"Votes":397,"Percentage":"34.82%","PoliticalParty":"Democratic"},{"BallotName":"Edward W. \"Ed\" Gillespie","BallotOrder":2,"Votes":724,"Percentage":"63.51%","PoliticalParty":"Republican"},{"BallotName":"Clifford D. Hyra","BallotOrder":3,"Votes":17,"Percentage":"1.49%","PoliticalParty":"Libertarian"},{"BallotName":"Write In","BallotOrder":2147483647,"Votes":2,"Percentage":"0.18%","PoliticalParty":"Write-In"}]},{"PrecinctName":"201 - SWEET HALL (01)","Candidates":[{"BallotName":"Ralph S. Northam","BallotOrder":1,"Votes":145,"Percentage":"34.28%","PoliticalParty":"Democratic"},{"BallotName":"Edward W. \"Ed\" Gillespie","BallotOrder":2,"Votes":269,"Percentage":"63.59%","PoliticalParty":"Republican"},{"BallotName":"Clifford D. Hyra","BallotOrder":3,"Votes":8,"Percentage":"1.89%","PoliticalParty":"Libertarian"},{"BallotName":"Write In","BallotOrder":2147483647,"Votes":1,"Percentage":"0.24%","PoliticalParty":"Write-In"}]},{"PrecinctName":"202 - COURTHOUSE (01)","Candidates":[{"BallotName":"Ralph S. Northam","BallotOrder":1,"Votes":326,"Percentage":"43.64%","PoliticalParty":"Democratic"},{"BallotName":"Edward W. \"Ed\" Gillespie","BallotOrder":2,"Votes":415,"Percentage":"55.56%","PoliticalParty":"Republican"},{"BallotName":"Clifford D. Hyra","BallotOrder":3,"Votes":6,"Percentage":"0.80%","PoliticalParty":"Libertarian"},{"BallotName":"Write In","BallotOrder":2147483647,"Votes":0,"Percentage":"0.00%","PoliticalParty":"Write-In"}]},{"PrecinctName":"301 - AYLETT (01)","Candidates":[{"BallotName":"Ralph S. Northam","BallotOrder":1,"Votes":275,"Percentage":"25.68%","PoliticalParty":"Democratic"},{"BallotName":"Edward W. \"Ed\" Gillespie","BallotOrder":2,"Votes":782,"Percentage":"73.02%","PoliticalParty":"Republican"},{"BallotName":"Clifford D. Hyra","BallotOrder":3,"Votes":13,"Percentage":"1.21%","PoliticalParty":"Libertarian"},{"BallotName":"Write In","BallotOrder":2147483647,"Votes":1,"Percentage":"0.09%","PoliticalParty":"Write-In"}]},{"PrecinctName":"401 - MANQUIN (01)","Candidates":[{"BallotName":"Ralph S. Northam","BallotOrder":1,"Votes":343,"Percentage":"30.04%","PoliticalParty":"Democratic"},{"BallotName":"Edward W. \"Ed\" Gillespie","BallotOrder":2,"Votes":793,"Percentage":"69.44%","PoliticalParty":"Republican"},{"BallotName":"Clifford D. Hyra","BallotOrder":3,"Votes":6,"Percentage":"0.53%","PoliticalParty":"Libertarian"},{"BallotName":"Write In","BallotOrder":2147483647,"Votes":0,"Percentage":"0.00%","PoliticalParty":"Write-In"}]},{"PrecinctName":"501 - MANGOHICK (01)","Candidates":[{"BallotName":"Ralph S. Northam","BallotOrder":1,"Votes":452,"Percentage":"36.72%","PoliticalParty":"Democratic"},{"BallotName":"Edward W. \"Ed\" Gillespie","BallotOrder":2,"Votes":768,"Percentage":"62.39%","PoliticalParty":"Republican"},{"BallotName":"Clifford D. Hyra","BallotOrder":3,"Votes":11,"Percentage":"0.89%","PoliticalParty":"Libertarian"},{"BallotName":"Write In","BallotOrder":2147483647,"Votes":0,"Percentage":"0.00%","PoliticalParty":"Write-In"}]}]}