{"ElectionName":"2017 November General","ElectionDate":"2017-11-07T00:00:00","CreateDate":"2017-11-13T19:06:45.138011-05:00","Locality":{"LocalityName":"CLARKE COUNTY","LocalityCode":"043"},"District":null,"RaceName":"Attorney General","NumberOfSeats":1,"Precincts":[{"PrecinctName":"# AB - Central Absentee Precinct (10)","Candidates":[{"BallotName":"Mark R. Herring","BallotOrder":1,"Votes":220,"Percentage":"51.89%","PoliticalParty":"Democratic"},{"BallotName":"John D. Adams","BallotOrder":2,"Votes":203,"Percentage":"47.88%","PoliticalParty":"Republican"},{"BallotName":"Write In","BallotOrder":2147483647,"Votes":1,"Percentage":"0.24%","PoliticalParty":"Write-In"}]},{"PrecinctName":"## Provisional (10)","Candidates":[{"BallotName":"Mark R. Herring","BallotOrder":1,"Votes":2,"Percentage":"50.00%","PoliticalParty":"Democratic"},{"BallotName":"John D. Adams","BallotOrder":2,"Votes":2,"Percentage":"50.00%","PoliticalParty":"Republican"},{"BallotName":"Write In","BallotOrder":2147483647,"Votes":0,"Percentage":"0.00%","PoliticalParty":"Write-In"}]},{"PrecinctName":"101 - RUSSELL (10)","Candidates":[{"BallotName":"Mark R. Herring","BallotOrder":1,"Votes":382,"Percentage":"36.21%","PoliticalParty":"Democratic"},{"BallotName":"John D. Adams","BallotOrder":2,"Votes":671,"Percentage":"63.60%","PoliticalParty":"Republican"},{"BallotName":"Write In","BallotOrder":2147483647,"Votes":2,"Percentage":"0.19%","PoliticalParty":"Write-In"}]},{"PrecinctName":"201 - BERRYVILLE (10)","Candidates":[{"BallotName":"Mark R. Herring","BallotOrder":1,"Votes":449,"Percentage":"48.86%","PoliticalParty":"Democratic"},{"BallotName":"John D. Adams","BallotOrder":2,"Votes":470,"Percentage":"51.14%","PoliticalParty":"Republican"},{"BallotName":"Write In","BallotOrder":2147483647,"Votes":0,"Percentage":"0.00%","PoliticalParty":"Write-In"}]},{"PrecinctName":"301 - MILLWOOD (10)","Candidates":[{"BallotName":"Mark R. Herring","BallotOrder":1,"Votes":339,"Percentage":"43.80%","PoliticalParty":"Democratic"},{"BallotName":"John D. Adams","BallotOrder":2,"Votes":435,"Percentage":"56.20%","PoliticalParty":"Republican"},{"BallotName":"Write In","BallotOrder":2147483647,"Votes":0,"Percentage":"0.00%","PoliticalParty":"Write-In"}]},{"PrecinctName":"302 - PINE GROVE (10)","Candidates":[{"BallotName":"Mark R. Herring","BallotOrder":1,"Votes":131,"Percentage":"38.19%","PoliticalParty":"Democratic"},{"BallotName":"John D. Adams","BallotOrder":2,"Votes":211,"Percentage":"61.52%","PoliticalParty":"Republican"},{"BallotName":"Write In","BallotOrder":2147483647,"Votes":1,"Percentage":"0.29%","PoliticalParty":"Write-In"}]},{"PrecinctName":"401 - WHITE POST (10)","Candidates":[{"BallotName":"Mark R. Herring","BallotOrder":1,"Votes":453,"Percentage":"45.07%","PoliticalParty":"Democratic"},{"BallotName":"John D. Adams","BallotOrder":2,"Votes":552,"Percentage":"54.93%","PoliticalParty":"Republican"},{"BallotName":"Write In","BallotOrder":2147483647,"Votes":0,"Percentage":"0.00%","PoliticalParty":"Write-In"}]},{"PrecinctName":"501 - BUCKMARSH (10)","Candidates":[{"BallotName":"Mark R. Herring","BallotOrder":1,"Votes":305,"Percentage":"41.67%","PoliticalParty":"Democratic"},{"BallotName":"John D. Adams","BallotOrder":2,"Votes":425,"Percentage":"58.06%","PoliticalParty":"Republican"},{"BallotName":"Write In","BallotOrder":2147483647,"Votes":2,"Percentage":"0.27%","PoliticalParty":"Write-In"}]},{"PrecinctName":"502 - BLUE RIDGE (10)","Candidates":[{"BallotName":"Mark R. Herring","BallotOrder":1,"Votes":128,"Percentage":"45.55%","PoliticalParty":"Democratic"},{"BallotName":"John D. Adams","BallotOrder":2,"Votes":153,"Percentage":"54.45%","PoliticalParty":"Republican"},{"BallotName":"Write In","BallotOrder":2147483647,"Votes":0,"Percentage":"0.00%","PoliticalParty":"Write-In"}]}]}