{"ElectionName":"2017 November General","ElectionDate":"2017-11-07T00:00:00","CreateDate":"2017-11-13T19:06:45.0009973-05:00","Locality":{"LocalityName":"CLARKE COUNTY","LocalityCode":"043"},"District":null,"RaceName":"Lieutenant Governor","NumberOfSeats":1,"Precincts":[{"PrecinctName":"# AB - Central Absentee Precinct (10)","Candidates":[{"BallotName":"Justin E. Fairfax","BallotOrder":1,"Votes":203,"Percentage":"47.88%","PoliticalParty":"Democratic"},{"BallotName":"Jill H. Vogel","BallotOrder":2,"Votes":220,"Percentage":"51.89%","PoliticalParty":"Republican"},{"BallotName":"Write In","BallotOrder":2147483647,"Votes":1,"Percentage":"0.24%","PoliticalParty":"Write-In"}]},{"PrecinctName":"## Provisional (10)","Candidates":[{"BallotName":"Justin E. Fairfax","BallotOrder":1,"Votes":1,"Percentage":"25.00%","PoliticalParty":"Democratic"},{"BallotName":"Jill H. Vogel","BallotOrder":2,"Votes":3,"Percentage":"75.00%","PoliticalParty":"Republican"},{"BallotName":"Write In","BallotOrder":2147483647,"Votes":0,"Percentage":"0.00%","PoliticalParty":"Write-In"}]},{"PrecinctName":"101 - RUSSELL (10)","Candidates":[{"BallotName":"Justin E. Fairfax","BallotOrder":1,"Votes":344,"Percentage":"32.58%","PoliticalParty":"Democratic"},{"BallotName":"Jill H. Vogel","BallotOrder":2,"Votes":712,"Percentage":"67.42%","PoliticalParty":"Republican"},{"BallotName":"Write In","BallotOrder":2147483647,"Votes":0,"Percentage":"0.00%","PoliticalParty":"Write-In"}]},{"PrecinctName":"201 - BERRYVILLE (10)","Candidates":[{"BallotName":"Justin E. Fairfax","BallotOrder":1,"Votes":417,"Percentage":"45.42%","PoliticalParty":"Democratic"},{"BallotName":"Jill H. Vogel","BallotOrder":2,"Votes":499,"Percentage":"54.36%","PoliticalParty":"Republican"},{"BallotName":"Write In","BallotOrder":2147483647,"Votes":2,"Percentage":"0.22%","PoliticalParty":"Write-In"}]},{"PrecinctName":"301 - MILLWOOD (10)","Candidates":[{"BallotName":"Justin E. Fairfax","BallotOrder":1,"Votes":321,"Percentage":"41.26%","PoliticalParty":"Democratic"},{"BallotName":"Jill H. Vogel","BallotOrder":2,"Votes":457,"Percentage":"58.74%","PoliticalParty":"Republican"},{"BallotName":"Write In","BallotOrder":2147483647,"Votes":0,"Percentage":"0.00%","PoliticalParty":"Write-In"}]},{"PrecinctName":"302 - PINE GROVE (10)","Candidates":[{"BallotName":"Justin E. Fairfax","BallotOrder":1,"Votes":128,"Percentage":"37.21%","PoliticalParty":"Democratic"},{"BallotName":"Jill H. Vogel","BallotOrder":2,"Votes":215,"Percentage":"62.50%","PoliticalParty":"Republican"},{"BallotName":"Write In","BallotOrder":2147483647,"Votes":1,"Percentage":"0.29%","PoliticalParty":"Write-In"}]},{"PrecinctName":"401 - WHITE POST (10)","Candidates":[{"BallotName":"Justin E. Fairfax","BallotOrder":1,"Votes":421,"Percentage":"41.60%","PoliticalParty":"Democratic"},{"BallotName":"Jill H. Vogel","BallotOrder":2,"Votes":590,"Percentage":"58.30%","PoliticalParty":"Republican"},{"BallotName":"Write In","BallotOrder":2147483647,"Votes":1,"Percentage":"0.10%","PoliticalParty":"Write-In"}]},{"PrecinctName":"501 - BUCKMARSH (10)","Candidates":[{"BallotName":"Justin E. Fairfax","BallotOrder":1,"Votes":288,"Percentage":"39.45%","PoliticalParty":"Democratic"},{"BallotName":"Jill H. Vogel","BallotOrder":2,"Votes":441,"Percentage":"60.41%","PoliticalParty":"Republican"},{"BallotName":"Write In","BallotOrder":2147483647,"Votes":1,"Percentage":"0.14%","PoliticalParty":"Write-In"}]},{"PrecinctName":"502 - BLUE RIDGE (10)","Candidates":[{"BallotName":"Justin E. Fairfax","BallotOrder":1,"Votes":124,"Percentage":"44.60%","PoliticalParty":"Democratic"},{"BallotName":"Jill H. Vogel","BallotOrder":2,"Votes":153,"Percentage":"55.04%","PoliticalParty":"Republican"},{"BallotName":"Write In","BallotOrder":2147483647,"Votes":1,"Percentage":"0.36%","PoliticalParty":"Write-In"}]}]}