{"ElectionName":"2017 November General","ElectionDate":"2017-11-07T00:00:00","CreateDate":"2017-11-13T19:07:03.6348023-05:00","Locality":{"LocalityName":"FREDERICK COUNTY","LocalityCode":"069"},"District":null,"RaceName":"Member Board of Supervisors (STONEWALL DISTRICT)","NumberOfSeats":1,"Precincts":[{"PrecinctName":"# AB - Central Absentee Precinct","Candidates":[{"BallotName":"Judith McCann-Slaughter","BallotOrder":1,"Votes":111,"Percentage":"97.37%","PoliticalParty":""},{"BallotName":"Write In","BallotOrder":2147483647,"Votes":3,"Percentage":"2.63%","PoliticalParty":""}]},{"PrecinctName":"## Provisional","Candidates":[{"BallotName":"Judith McCann-Slaughter","BallotOrder":1,"Votes":0,"Percentage":"0.00%","PoliticalParty":""},{"BallotName":"Write In","BallotOrder":2147483647,"Votes":0,"Percentage":"0.00%","PoliticalParty":""}]},{"PrecinctName":"301 - CLEAR BROOK","Candidates":[{"BallotName":"Judith McCann-Slaughter","BallotOrder":1,"Votes":522,"Percentage":"96.49%","PoliticalParty":""},{"BallotName":"Write In","BallotOrder":2147483647,"Votes":19,"Percentage":"3.51%","PoliticalParty":""}]},{"PrecinctName":"302 - NEFF'S TOWN","Candidates":[{"BallotName":"Judith McCann-Slaughter","BallotOrder":1,"Votes":1027,"Percentage":"96.43%","PoliticalParty":""},{"BallotName":"Write In","BallotOrder":2147483647,"Votes":38,"Percentage":"3.57%","PoliticalParty":""}]},{"PrecinctName":"303 - WHITE HALL","Candidates":[{"BallotName":"Judith McCann-Slaughter","BallotOrder":1,"Votes":1226,"Percentage":"97.77%","PoliticalParty":""},{"BallotName":"Write In","BallotOrder":2147483647,"Votes":28,"Percentage":"2.23%","PoliticalParty":""}]}]}