{"ElectionName":"2017 November General","ElectionDate":"2017-11-07T00:00:00","CreateDate":"2017-11-13T19:07:08.930093-05:00","Locality":{"LocalityName":"GREENE COUNTY","LocalityCode":"079"},"District":null,"RaceName":"Member School Board (STANARDSVILLE DISTRICT)","NumberOfSeats":1,"Precincts":[{"PrecinctName":"# AB - Central Absentee Precinct","Candidates":[{"BallotName":"Jason K. Collier","BallotOrder":1,"Votes":108,"Percentage":"99.08%","PoliticalParty":""},{"BallotName":"Write In","BallotOrder":2147483647,"Votes":1,"Percentage":"0.92%","PoliticalParty":""}]},{"PrecinctName":"## Provisional","Candidates":[{"BallotName":"Jason K. Collier","BallotOrder":1,"Votes":1,"Percentage":"100.00%","PoliticalParty":""},{"BallotName":"Write In","BallotOrder":2147483647,"Votes":0,"Percentage":"0.00%","PoliticalParty":""}]},{"PrecinctName":"301 - STANARDSVILLE","Candidates":[{"BallotName":"Jason K. Collier","BallotOrder":1,"Votes":1103,"Percentage":"97.87%","PoliticalParty":""},{"BallotName":"Write In","BallotOrder":2147483647,"Votes":24,"Percentage":"2.13%","PoliticalParty":""}]}]}