{"ElectionName":"2017 November General","ElectionDate":"2017-11-07T00:00:00","CreateDate":"2017-11-13T19:06:56.9721943-05:00","Locality":{"LocalityName":"FAIRFAX COUNTY","LocalityCode":"059"},"District":null,"RaceName":"Member House of Delegates (039)","NumberOfSeats":1,"Precincts":[{"PrecinctName":"# AB - Central Absentee Precinct (039)","Candidates":[{"BallotName":"Vivian E. Watts","BallotOrder":1,"Votes":2003,"Percentage":"92.13%","PoliticalParty":"Democratic"},{"BallotName":"Write In","BallotOrder":2147483647,"Votes":171,"Percentage":"7.87%","PoliticalParty":"Write-In"}]},{"PrecinctName":"## Provisional (039)","Candidates":[{"BallotName":"Vivian E. Watts","BallotOrder":1,"Votes":15,"Percentage":"100.00%","PoliticalParty":"Democratic"},{"BallotName":"Write In","BallotOrder":2147483647,"Votes":0,"Percentage":"0.00%","PoliticalParty":"Write-In"}]},{"PrecinctName":"104 - CHAPEL (039)","Candidates":[{"BallotName":"Vivian E. Watts","BallotOrder":1,"Votes":985,"Percentage":"88.74%","PoliticalParty":"Democratic"},{"BallotName":"Write In","BallotOrder":2147483647,"Votes":125,"Percentage":"11.26%","PoliticalParty":"Write-In"}]},{"PrecinctName":"108 - KINGS PARK (039)","Candidates":[{"BallotName":"Vivian E. Watts","BallotOrder":1,"Votes":946,"Percentage":"89.41%","PoliticalParty":"Democratic"},{"BallotName":"Write In","BallotOrder":2147483647,"Votes":112,"Percentage":"10.59%","PoliticalParty":"Write-In"}]},{"PrecinctName":"110 - NORTH SPRINGFIELD (039)","Candidates":[{"BallotName":"Vivian E. Watts","BallotOrder":1,"Votes":1468,"Percentage":"90.90%","PoliticalParty":"Democratic"},{"BallotName":"Write In","BallotOrder":2147483647,"Votes":147,"Percentage":"9.10%","PoliticalParty":"Write-In"}]},{"PrecinctName":"113 - CANTERBURY (039)","Candidates":[{"BallotName":"Vivian E. Watts","BallotOrder":1,"Votes":1641,"Percentage":"92.24%","PoliticalParty":"Democratic"},{"BallotName":"Write In","BallotOrder":2147483647,"Votes":138,"Percentage":"7.76%","PoliticalParty":"Write-In"}]},{"PrecinctName":"115 - RAVENSWORTH (039)","Candidates":[{"BallotName":"Vivian E. Watts","BallotOrder":1,"Votes":647,"Percentage":"89.99%","PoliticalParty":"Democratic"},{"BallotName":"Write In","BallotOrder":2147483647,"Votes":72,"Percentage":"10.01%","PoliticalParty":"Write-In"}]},{"PrecinctName":"116 - WAKEFIELD (039)","Candidates":[{"BallotName":"Vivian E. Watts","BallotOrder":1,"Votes":1071,"Percentage":"92.01%","PoliticalParty":"Democratic"},{"BallotName":"Write In","BallotOrder":2147483647,"Votes":93,"Percentage":"7.99%","PoliticalParty":"Write-In"}]},{"PrecinctName":"133 - DANBURY (039)","Candidates":[{"BallotName":"Vivian E. Watts","BallotOrder":1,"Votes":279,"Percentage":"92.08%","PoliticalParty":"Democratic"},{"BallotName":"Write In","BallotOrder":2147483647,"Votes":24,"Percentage":"7.92%","PoliticalParty":"Write-In"}]},{"PrecinctName":"403 - FORESTDALE (039)","Candidates":[{"BallotName":"Vivian E. Watts","BallotOrder":1,"Votes":514,"Percentage":"92.61%","PoliticalParty":"Democratic"},{"BallotName":"Write In","BallotOrder":2147483647,"Votes":41,"Percentage":"7.39%","PoliticalParty":"Write-In"}]},{"PrecinctName":"409 - PIONEER (039)","Candidates":[{"BallotName":"Vivian E. Watts","BallotOrder":1,"Votes":1319,"Percentage":"95.23%","PoliticalParty":"Democratic"},{"BallotName":"Write In","BallotOrder":2147483647,"Votes":66,"Percentage":"4.77%","PoliticalParty":"Write-In"}]},{"PrecinctName":"415 - CRESTWOOD (039)","Candidates":[{"BallotName":"Vivian E. Watts","BallotOrder":1,"Votes":929,"Percentage":"92.62%","PoliticalParty":"Democratic"},{"BallotName":"Write In","BallotOrder":2147483647,"Votes":74,"Percentage":"7.38%","PoliticalParty":"Write-In"}]},{"PrecinctName":"417 - GARFIELD (039)","Candidates":[{"BallotName":"Vivian E. Watts","BallotOrder":1,"Votes":1221,"Percentage":"93.14%","PoliticalParty":"Democratic"},{"BallotName":"Write In","BallotOrder":2147483647,"Votes":90,"Percentage":"6.86%","PoliticalParty":"Write-In"}]},{"PrecinctName":"418 - LYNBROOK (039)","Candidates":[{"BallotName":"Vivian E. Watts","BallotOrder":1,"Votes":713,"Percentage":"94.56%","PoliticalParty":"Democratic"},{"BallotName":"Write In","BallotOrder":2147483647,"Votes":41,"Percentage":"5.44%","PoliticalParty":"Write-In"}]},{"PrecinctName":"419 - LANE (039)","Candidates":[{"BallotName":"Vivian E. Watts","BallotOrder":1,"Votes":841,"Percentage":"94.07%","PoliticalParty":"Democratic"},{"BallotName":"Write In","BallotOrder":2147483647,"Votes":53,"Percentage":"5.93%","PoliticalParty":"Write-In"}]},{"PrecinctName":"426 - GREENSPRING (039)","Candidates":[{"BallotName":"Vivian E. Watts","BallotOrder":1,"Votes":873,"Percentage":"98.09%","PoliticalParty":"Democratic"},{"BallotName":"Write In","BallotOrder":2147483647,"Votes":17,"Percentage":"1.91%","PoliticalParty":"Write-In"}]},{"PrecinctName":"516 - WEYANOKE (039)","Candidates":[{"BallotName":"Vivian E. Watts","BallotOrder":1,"Votes":485,"Percentage":"91.86%","PoliticalParty":"Democratic"},{"BallotName":"Write In","BallotOrder":2147483647,"Votes":43,"Percentage":"8.14%","PoliticalParty":"Write-In"}]},{"PrecinctName":"522 - CAMELOT (039)","Candidates":[{"BallotName":"Vivian E. Watts","BallotOrder":1,"Votes":443,"Percentage":"90.41%","PoliticalParty":"Democratic"},{"BallotName":"Write In","BallotOrder":2147483647,"Votes":47,"Percentage":"9.59%","PoliticalParty":"Write-In"}]},{"PrecinctName":"526 - BREN MAR (039)","Candidates":[{"BallotName":"Vivian E. Watts","BallotOrder":1,"Votes":1302,"Percentage":"95.81%","PoliticalParty":"Democratic"},{"BallotName":"Write In","BallotOrder":2147483647,"Votes":57,"Percentage":"4.19%","PoliticalParty":"Write-In"}]},{"PrecinctName":"527 - EDSALL (039)","Candidates":[{"BallotName":"Vivian E. Watts","BallotOrder":1,"Votes":768,"Percentage":"93.66%","PoliticalParty":"Democratic"},{"BallotName":"Write In","BallotOrder":2147483647,"Votes":52,"Percentage":"6.34%","PoliticalParty":"Write-In"}]},{"PrecinctName":"528 - RIDGELEA (039)","Candidates":[{"BallotName":"Vivian E. Watts","BallotOrder":1,"Votes":552,"Percentage":"91.54%","PoliticalParty":"Democratic"},{"BallotName":"Write In","BallotOrder":2147483647,"Votes":51,"Percentage":"8.46%","PoliticalParty":"Write-In"}]},{"PrecinctName":"623 - ALBAN (039)","Candidates":[{"BallotName":"Vivian E. Watts","BallotOrder":1,"Votes":1097,"Percentage":"94.16%","PoliticalParty":"Democratic"},{"BallotName":"Write In","BallotOrder":2147483647,"Votes":68,"Percentage":"5.84%","PoliticalParty":"Write-In"}]},{"PrecinctName":"626 - SARATOGA (039)","Candidates":[{"BallotName":"Vivian E. Watts","BallotOrder":1,"Votes":1295,"Percentage":"91.33%","PoliticalParty":"Democratic"},{"BallotName":"Write In","BallotOrder":2147483647,"Votes":123,"Percentage":"8.67%","PoliticalParty":"Write-In"}]}]}