{"ElectionName":"2017 November General","ElectionDate":"2017-11-07T00:00:00","CreateDate":"2017-11-13T19:08:04.3502717-05:00","Locality":{"LocalityName":"SHENANDOAH COUNTY","LocalityCode":"171"},"District":null,"RaceName":"Member House of Delegates (015)","NumberOfSeats":1,"Precincts":[{"PrecinctName":"# AB - Central Absentee Precinct (015)","Candidates":[{"BallotName":"C. Todd Gilbert","BallotOrder":1,"Votes":446,"Percentage":"87.45%","PoliticalParty":"Republican"},{"BallotName":"Write In","BallotOrder":2147483647,"Votes":64,"Percentage":"12.55%","PoliticalParty":"Write-In"}]},{"PrecinctName":"## Provisional (015)","Candidates":[{"BallotName":"C. Todd Gilbert","BallotOrder":1,"Votes":6,"Percentage":"100.00%","PoliticalParty":"Republican"},{"BallotName":"Write In","BallotOrder":2147483647,"Votes":0,"Percentage":"0.00%","PoliticalParty":"Write-In"}]},{"PrecinctName":"101 - ORKNEY SPRINGS (015)","Candidates":[{"BallotName":"C. Todd Gilbert","BallotOrder":1,"Votes":488,"Percentage":"92.95%","PoliticalParty":"Republican"},{"BallotName":"Write In","BallotOrder":2147483647,"Votes":37,"Percentage":"7.05%","PoliticalParty":"Write-In"}]},{"PrecinctName":"103 - NEW MARKET (015)","Candidates":[{"BallotName":"C. Todd Gilbert","BallotOrder":1,"Votes":1211,"Percentage":"96.73%","PoliticalParty":"Republican"},{"BallotName":"Write In","BallotOrder":2147483647,"Votes":41,"Percentage":"3.27%","PoliticalParty":"Write-In"}]},{"PrecinctName":"201 - CONICVILLE (015)","Candidates":[{"BallotName":"C. Todd Gilbert","BallotOrder":1,"Votes":848,"Percentage":"93.91%","PoliticalParty":"Republican"},{"BallotName":"Write In","BallotOrder":2147483647,"Votes":55,"Percentage":"6.09%","PoliticalParty":"Write-In"}]},{"PrecinctName":"202 - MT JACKSON (015)","Candidates":[{"BallotName":"C. Todd Gilbert","BallotOrder":1,"Votes":714,"Percentage":"94.07%","PoliticalParty":"Republican"},{"BallotName":"Write In","BallotOrder":2147483647,"Votes":45,"Percentage":"5.93%","PoliticalParty":"Write-In"}]},{"PrecinctName":"302 - EDINBURG (015)","Candidates":[{"BallotName":"C. Todd Gilbert","BallotOrder":1,"Votes":781,"Percentage":"92.32%","PoliticalParty":"Republican"},{"BallotName":"Write In","BallotOrder":2147483647,"Votes":65,"Percentage":"7.68%","PoliticalParty":"Write-In"}]},{"PrecinctName":"303 - ST LUKE (015)","Candidates":[{"BallotName":"C. Todd Gilbert","BallotOrder":1,"Votes":849,"Percentage":"95.93%","PoliticalParty":"Republican"},{"BallotName":"Write In","BallotOrder":2147483647,"Votes":36,"Percentage":"4.07%","PoliticalParty":"Write-In"}]},{"PrecinctName":"304 - FORT VALLEY (015)","Candidates":[{"BallotName":"C. Todd Gilbert","BallotOrder":1,"Votes":427,"Percentage":"91.83%","PoliticalParty":"Republican"},{"BallotName":"Write In","BallotOrder":2147483647,"Votes":38,"Percentage":"8.17%","PoliticalParty":"Write-In"}]},{"PrecinctName":"401 - WOODSTOCK (015)","Candidates":[{"BallotName":"C. Todd Gilbert","BallotOrder":1,"Votes":1594,"Percentage":"92.41%","PoliticalParty":"Republican"},{"BallotName":"Write In","BallotOrder":2147483647,"Votes":131,"Percentage":"7.59%","PoliticalParty":"Write-In"}]},{"PrecinctName":"501 - CEDAR CREEK (015)","Candidates":[{"BallotName":"C. Todd Gilbert","BallotOrder":1,"Votes":74,"Percentage":"91.36%","PoliticalParty":"Republican"},{"BallotName":"Write In","BallotOrder":2147483647,"Votes":7,"Percentage":"8.64%","PoliticalParty":"Write-In"}]},{"PrecinctName":"503 - TOMS BROOK (015)","Candidates":[{"BallotName":"C. Todd Gilbert","BallotOrder":1,"Votes":1121,"Percentage":"94.04%","PoliticalParty":"Republican"},{"BallotName":"Write In","BallotOrder":2147483647,"Votes":71,"Percentage":"5.96%","PoliticalParty":"Write-In"}]},{"PrecinctName":"504 - LEBANON CHURCH (015)","Candidates":[{"BallotName":"C. Todd Gilbert","BallotOrder":1,"Votes":726,"Percentage":"97.32%","PoliticalParty":"Republican"},{"BallotName":"Write In","BallotOrder":2147483647,"Votes":20,"Percentage":"2.68%","PoliticalParty":"Write-In"}]},{"PrecinctName":"601 - STRASBURG (015)","Candidates":[{"BallotName":"C. Todd Gilbert","BallotOrder":1,"Votes":1200,"Percentage":"88.69%","PoliticalParty":"Republican"},{"BallotName":"Write In","BallotOrder":2147483647,"Votes":153,"Percentage":"11.31%","PoliticalParty":"Write-In"}]}]}